laurium/__init__.py
laurium/components/__init__.py
laurium/components/evaluate_metrics.py
laurium/components/extract_context.py
laurium/components/generate_pii.py
laurium/components/load.py
laurium/components/utils.py
laurium/decoder_models/__init__.py
laurium/decoder_models/extract.py
laurium/decoder_models/llm.py
laurium/decoder_models/prompts.py
laurium/decoder_models/pydantic_models.py
laurium/encoder_models/__init__.py
laurium/encoder_models/fine_tune.py
laurium/encoder_models/nli.py
laurium/encoder_models/preprocess.py
laurium-0.4.2.dist-info/METADATA
laurium-0.4.2.dist-info/WHEEL
laurium-0.4.2.dist-info/licenses/LICENSE
laurium-0.4.2.dist-info/RECORD
