Metadata-Version: 2.4
Name: laurium
Version: 0.4.2
Summary: A package for extracting structured data from free text
Project-URL: homepage, https://github.com/moj-analytical-services/laurium
Project-URL: repository, https://github.com/moj-analytical-services/laurium
Project-URL: documentation, https://moj-analytical-services.github.io/laurium
Author-email: Tom O'Connor <tom.oconnor@justice.gov.uk>, William Martin <william.martin1@justice.gov.uk>, Lisa Malki <lisa.Malki@justice.gov.uk>, Daoud Chaudry <daoud.chaudry@justice.gov.uk>
License-File: LICENSE
Classifier: Operating System :: OS Independent
Classifier: Programming Language :: Python :: 3
Requires-Python: >=3.13
Requires-Dist: altair>=5.5.0
Requires-Dist: boto3>=1.34.0
Requires-Dist: en-core-web-sm
Requires-Dist: evaluate>=0.4.3
Requires-Dist: faker>=37.3.0
Requires-Dist: hydra-core>=1.3.2
Requires-Dist: langchain-anthropic>=0.0.4
Requires-Dist: langchain-aws>=0.2.7
Requires-Dist: langchain-community>=0.0.16
Requires-Dist: langchain-core>=0.1.30
Requires-Dist: langchain-ollama>=0.0.2
Requires-Dist: langchain-openai>=0.0.5
Requires-Dist: marimo>=0.14.11
Requires-Dist: mlflow>=2.22.0
Requires-Dist: numpy>=2.0.0
Requires-Dist: omegaconf>=2.3.0
Requires-Dist: pandas>=2.2.2
Requires-Dist: pip>=24.2
Requires-Dist: protobuf>=5.28.1
Requires-Dist: pydantic>=2.6.3
Requires-Dist: pydbtools
Requires-Dist: pytest>=8.3.2
Requires-Dist: spacy==3.8.7
Provides-Extra: encoder
Requires-Dist: datasets>=3.6.0; extra == 'encoder'
Requires-Dist: optuna>=4.5.0; extra == 'encoder'
Requires-Dist: peft>=0.15.2; extra == 'encoder'
Requires-Dist: pytorch-lightning>=2.5.2; extra == 'encoder'
Requires-Dist: torch>=2.4.0; extra == 'encoder'
Requires-Dist: transformers>=4.44.2; extra == 'encoder'
